livekit_openai_agents/__init__.py
livekit_openai_agents/adapter/__init__.py
livekit_openai_agents/adapter/adapter.py
livekit_openai_agents/adapter/utils.py
livekit_openai_agents-0.2.5.dist-info/licenses/LICENSE
livekit_openai_agents-0.2.5.dist-info/METADATA
livekit_openai_agents-0.2.5.dist-info/WHEEL
livekit_openai_agents-0.2.5.dist-info/top_level.txt
livekit_openai_agents-0.2.5.dist-info/RECORD
