Metadata-Version: 2.4
Name: livekit_openai_agents
Version: 0.2.5
Summary: An adapter to integrate OpenAI Agents as LLM providers for LiveKit.
Author-email: Anil Berk Altuner <altuneranilberk@gmail.com>
License: MIT
Project-URL: Homepage, https://github.com/anilaltuner/livekit-openai-agents
Project-URL: Bug Tracker, https://github.com/anilaltuner/livekit-openai-agents
Classifier: Programming Language :: Python :: 3
Classifier: Programming Language :: Python :: 3.11
Classifier: Operating System :: OS Independent
Classifier: Topic :: Multimedia :: Sound/Audio :: Speech
Classifier: Topic :: Scientific/Engineering :: Artificial Intelligence
Requires-Python: <4.0,>=3.11
License-File: LICENSE
Requires-Dist: livekit-agents==1.1.3
Requires-Dist: openai-agents>=0.0.14
Requires-Dist: pyee>=9.0.0
Dynamic: license-file
